{
"meta":{"test_sets":[],"test_metrics":[],"learn_metrics":[{"best_value":"Min","name":"Logloss"}],"launch_mode":"Train","parameters":"","iteration_count":100,"learn_sets":["learn"],"name":"experiment"},
"iterations":[
{"learn":[0.6844004212],"iteration":0,"passed_time":0.02171802525,"remaining_time":2.1500845},
{"learn":[0.6773712708],"iteration":1,"passed_time":0.03855948693,"remaining_time":1.88941486},
{"learn":[0.6716570075],"iteration":2,"passed_time":0.05904654447,"remaining_time":1.909171604},
{"learn":[0.6668525277],"iteration":3,"passed_time":0.07832656945,"remaining_time":1.879837667},
{"learn":[0.6627164448],"iteration":4,"passed_time":0.09639454623,"remaining_time":1.831496378},
{"learn":[0.6591686404],"iteration":5,"passed_time":0.1158859324,"remaining_time":1.815546275},
{"learn":[0.6563500715],"iteration":6,"passed_time":0.1353069774,"remaining_time":1.797649842},
{"learn":[0.6538198743],"iteration":7,"passed_time":0.1555662939,"remaining_time":1.789012379},
{"learn":[0.6517354441],"iteration":8,"passed_time":0.1816456075,"remaining_time":1.836638921},
{"learn":[0.64983981],"iteration":9,"passed_time":0.2072478663,"remaining_time":1.865230797},
{"learn":[0.6481704529],"iteration":10,"passed_time":0.2295250368,"remaining_time":1.857066207},
{"learn":[0.6468150728],"iteration":11,"passed_time":0.2500799184,"remaining_time":1.833919402},
{"learn":[0.6454827826],"iteration":12,"passed_time":0.2750544513,"remaining_time":1.84074902},
{"learn":[0.6443716557],"iteration":13,"passed_time":0.2934566301,"remaining_time":1.802662156},
{"learn":[0.6434963411],"iteration":14,"passed_time":0.3138594672,"remaining_time":1.778536981},
{"learn":[0.6425926769],"iteration":15,"passed_time":0.3333664471,"remaining_time":1.750173847},
{"learn":[0.641898306],"iteration":16,"passed_time":0.3521914716,"remaining_time":1.719523067},
{"learn":[0.6412424636],"iteration":17,"passed_time":0.3752090389,"remaining_time":1.709285622},
{"learn":[0.640743196],"iteration":18,"passed_time":0.392185832,"remaining_time":1.671950126},
{"learn":[0.6402351456],"iteration":19,"passed_time":0.4140239246,"remaining_time":1.656095698},
{"learn":[0.6398017628],"iteration":20,"passed_time":0.4364853713,"remaining_time":1.642016397},
{"learn":[0.639373895],"iteration":21,"passed_time":0.4624455184,"remaining_time":1.639579565},
{"learn":[0.6389535574],"iteration":22,"passed_time":0.4863360918,"remaining_time":1.628168655},
{"learn":[0.6385615529],"iteration":23,"passed_time":0.5118930627,"remaining_time":1.620994699},
{"learn":[0.6382481895],"iteration":24,"passed_time":0.545382328,"remaining_time":1.636146984},
{"learn":[0.6377929497],"iteration":25,"passed_time":0.5904753524,"remaining_time":1.680583695},
{"learn":[0.637304893],"iteration":26,"passed_time":0.6337171704,"remaining_time":1.713383461},
{"learn":[0.6370456034],"iteration":27,"passed_time":0.6715158377,"remaining_time":1.726755011},
{"learn":[0.636671276],"iteration":28,"passed_time":0.7105136356,"remaining_time":1.739533384},
{"learn":[0.6364867741],"iteration":29,"passed_time":0.7400137387,"remaining_time":1.726698724},
{"learn":[0.6362253787],"iteration":30,"passed_time":0.7667075459,"remaining_time":1.706542602},
{"learn":[0.635934325],"iteration":31,"passed_time":0.7903687813,"remaining_time":1.67953366},
{"learn":[0.6356867949],"iteration":32,"passed_time":0.8117217062,"remaining_time":1.64804104},
{"learn":[0.635482769],"iteration":33,"passed_time":0.8298782178,"remaining_time":1.61094007},
{"learn":[0.6352806673],"iteration":34,"passed_time":0.8509825493,"remaining_time":1.580396163},
{"learn":[0.6350792693],"iteration":35,"passed_time":0.8774162507,"remaining_time":1.559851112},
{"learn":[0.6349010567],"iteration":36,"passed_time":0.8947776318,"remaining_time":1.523540292},
{"learn":[0.6347384736],"iteration":37,"passed_time":0.923701895,"remaining_time":1.507092565},
{"learn":[0.6345790357],"iteration":38,"passed_time":0.9449231037,"remaining_time":1.477956649},
{"learn":[0.6344627923],"iteration":39,"passed_time":0.9670376914,"remaining_time":1.450556537},
{"learn":[0.6342413656],"iteration":40,"passed_time":0.985157358,"remaining_time":1.417665466},
{"learn":[0.6340378033],"iteration":41,"passed_time":1.009963216,"remaining_time":1.394711108},
{"learn":[0.6338739619],"iteration":42,"passed_time":1.02899783,"remaining_time":1.36402038},
{"learn":[0.6337698543],"iteration":43,"passed_time":1.048062553,"remaining_time":1.333897795},
{"learn":[0.6336774264],"iteration":44,"passed_time":1.06844246,"remaining_time":1.305874117},
{"learn":[0.6334999894],"iteration":45,"passed_time":1.088558429,"remaining_time":1.277872939},
{"learn":[0.6333974194],"iteration":46,"passed_time":1.109328528,"remaining_time":1.250944936},
{"learn":[0.6332386527],"iteration":47,"passed_time":1.130709694,"remaining_time":1.224935502},
{"learn":[0.633163241],"iteration":48,"passed_time":1.156383783,"remaining_time":1.203583122},
{"learn":[0.6329860371],"iteration":49,"passed_time":1.181830213,"remaining_time":1.181830213},
{"learn":[0.6328646432],"iteration":50,"passed_time":1.207007121,"remaining_time":1.159673508},
{"learn":[0.6327242086],"iteration":51,"passed_time":1.230332213,"remaining_time":1.135691274},
{"learn":[0.6326159882],"iteration":52,"passed_time":1.256397288,"remaining_time":1.114163632},
{"learn":[0.6325281363],"iteration":53,"passed_time":1.277463305,"remaining_time":1.088209482},
{"learn":[0.6324072352],"iteration":54,"passed_time":1.305154497,"remaining_time":1.06785368},
{"learn":[0.6322730697],"iteration":55,"passed_time":1.330857752,"remaining_time":1.045673948},
{"learn":[0.6322041868],"iteration":56,"passed_time":1.363677002,"remaining_time":1.028738791},
{"learn":[0.6321192406],"iteration":57,"passed_time":1.386591693,"remaining_time":1.00408364},
{"learn":[0.6320515077],"iteration":58,"passed_time":1.407853117,"remaining_time":0.9783386069},
{"learn":[0.6319483244],"iteration":59,"passed_time":1.43061561,"remaining_time":0.9537437402},
{"learn":[0.631844033],"iteration":60,"passed_time":1.457541784,"remaining_time":0.9318709764},
{"learn":[0.6317805651],"iteration":61,"passed_time":1.480150335,"remaining_time":0.9071889149},
{"learn":[0.6317138817],"iteration":62,"passed_time":1.509048981,"remaining_time":0.8862668617},
{"learn":[0.631635889],"iteration":63,"passed_time":1.528468161,"remaining_time":0.8597633406},
{"learn":[0.6315342571],"iteration":64,"passed_time":1.562425648,"remaining_time":0.8413061181},
{"learn":[0.6314554861],"iteration":65,"passed_time":1.584031812,"remaining_time":0.8160163879},
{"learn":[0.6314127563],"iteration":66,"passed_time":1.613780288,"remaining_time":0.7948470075},
{"learn":[0.6313581579],"iteration":67,"passed_time":1.639059808,"remaining_time":0.7713222626},
{"learn":[0.6313079227],"iteration":68,"passed_time":1.661761403,"remaining_time":0.7465884566},
{"learn":[0.6312249362],"iteration":69,"passed_time":1.688892307,"remaining_time":0.7238109888},
{"learn":[0.6311814339],"iteration":70,"passed_time":1.713955115,"remaining_time":0.7000661736},
{"learn":[0.631142183],"iteration":71,"passed_time":1.735180757,"remaining_time":0.6747925165},
{"learn":[0.6310928012],"iteration":72,"passed_time":1.753902687,"remaining_time":0.6487037334},
{"learn":[0.6310534457],"iteration":73,"passed_time":1.774989851,"remaining_time":0.6236450827},
{"learn":[0.6310263874],"iteration":74,"passed_time":1.800453526,"remaining_time":0.6001511755},
{"learn":[0.6309620273],"iteration":75,"passed_time":1.821497287,"remaining_time":0.5752096695},
{"learn":[0.6309116495],"iteration":76,"passed_time":1.845882917,"remaining_time":0.5513676244},
{"learn":[0.6308373257],"iteration":77,"passed_time":1.882956522,"remaining_time":0.531090301},
{"learn":[0.6308052966],"iteration":78,"passed_time":1.907495131,"remaining_time":0.5070556678},
{"learn":[0.6307532106],"iteration":79,"passed_time":1.930467892,"remaining_time":0.482616973},
{"learn":[0.6307080078],"iteration":80,"passed_time":1.958781212,"remaining_time":0.4594671978},
{"learn":[0.63065963],"iteration":81,"passed_time":1.980330114,"remaining_time":0.4347066104},
{"learn":[0.6306035337],"iteration":82,"passed_time":2.008905744,"remaining_time":0.4114626223},
{"learn":[0.630549254],"iteration":83,"passed_time":2.0398774,"remaining_time":0.3885480761},
{"learn":[0.6304559393],"iteration":84,"passed_time":2.066050874,"remaining_time":0.3645972131},
{"learn":[0.630401455],"iteration":85,"passed_time":2.089133228,"remaining_time":0.3400914556},
{"learn":[0.630355365],"iteration":86,"passed_time":2.119117796,"remaining_time":0.3166497855},
{"learn":[0.6303293983],"iteration":87,"passed_time":2.139896587,"remaining_time":0.29180408},
{"learn":[0.6302815991],"iteration":88,"passed_time":2.161343832,"remaining_time":0.2671323838},
{"learn":[0.6302128393],"iteration":89,"passed_time":2.189123623,"remaining_time":0.2432359581},
{"learn":[0.6301561227],"iteration":90,"passed_time":2.212298153,"remaining_time":0.2187987184},
{"learn":[0.6301089829],"iteration":91,"passed_time":2.236349226,"remaining_time":0.1944651501},
{"learn":[0.630066194],"iteration":92,"passed_time":2.25822864,"remaining_time":0.1699741987},
{"learn":[0.6300154469],"iteration":93,"passed_time":2.274861615,"remaining_time":0.1452039329},
{"learn":[0.6299733324],"iteration":94,"passed_time":2.303055172,"remaining_time":0.1212134301},
{"learn":[0.6299414642],"iteration":95,"passed_time":2.323500957,"remaining_time":0.09681253988},
{"learn":[0.6299001192],"iteration":96,"passed_time":2.346755938,"remaining_time":0.07258008056},
{"learn":[0.6298696853],"iteration":97,"passed_time":2.362888689,"remaining_time":0.04822221814},
{"learn":[0.6298324031],"iteration":98,"passed_time":2.392082598,"remaining_time":0.02416245049},
{"learn":[0.629756828],"iteration":99,"passed_time":2.408949655,"remaining_time":0}
]}